nonebot_plugin_botoffline_email/__init__.py
nonebot_plugin_botoffline_email/config.py
nonebot_plugin_botoffline_email/handlers.py
nonebot_plugin_botoffline_email-0.0.4.dist-info/LICENSE
nonebot_plugin_botoffline_email-0.0.4.dist-info/METADATA
nonebot_plugin_botoffline_email-0.0.4.dist-info/WHEEL
nonebot_plugin_botoffline_email-0.0.4.dist-info/RECORD
