Metadata-Version: 2.3
Name: nonebot-plugin-botoffline-email
Version: 0.0.4
Summary: QQ Bot 掉线后使用 SMTP 发送邮件提醒
Keywords: nonebot,nonebot2,plugin,botoffline,smtp,email
Author: 千秋紫莹
Author-email: qianqiuzy@gmail.com
Requires-Python: >=3.9,<4.0
Classifier: Programming Language :: Python :: 3
Classifier: Programming Language :: Python :: 3.9
Classifier: Programming Language :: Python :: 3.10
Classifier: Programming Language :: Python :: 3.11
Classifier: Programming Language :: Python :: 3.12
Classifier: Programming Language :: Python :: 3.13
Requires-Dist: nonebot-adapter-onebot (>=2.0.0-beta.1)
Requires-Dist: nonebot2 (>=2.3.0,<3.0.0)
Requires-Dist: nonebot_plugin_apscheduler (>=0.4.0)
Requires-Dist: pydantic (>=2.0,<3.0)
Requires-Dist: pydantic-settings (>=2.0,<3.0)
Requires-Dist: python-dotenv (>=1.0,<2.0)
Project-URL: Repository, https://github.com/qianqiuzy/nonebot-plugin-botoffline-email
